<annotation>
	<folder></folder>
	<filename>b176b317-68a9-4c38-ac39-55e5244c9b9c___60653-jpg_jpeg.rf.bb1c945d8be3b2357b59bb43fc9c6613.jpg</filename>
	<path>b176b317-68a9-4c38-ac39-55e5244c9b9c___60653-jpg_jpeg.rf.bb1c945d8be3b2357b59bb43fc9c6613.jpg</path>
	<source>
		<database>roboflow.com</database>
	</source>
	<size>
		<width>640</width>
		<height>640</height>
		<depth>3</depth>
	</size>
	<segmented>0</segmented>
	<object>
		<name>Plate</name>
		<pose>Unspecified</pose>
		<truncated>0</truncated>
		<difficult>0</difficult>
		<occluded>0</occluded>
		<bndbox>
			<xmin>310</xmin>
			<xmax>564</xmax>
			<ymin>209</ymin>
			<ymax>504</ymax>
		</bndbox>
	</object>
</annotation>
