<annotation>
	<folder></folder>
	<filename>video4_2730_jpg.rf.90b9fe3708caa42937227cbfdb94eac8.jpg</filename>
	<path>video4_2730_jpg.rf.90b9fe3708caa42937227cbfdb94eac8.jpg</path>
	<source>
		<database>roboflow.com</database>
	</source>
	<size>
		<width>640</width>
		<height>640</height>
		<depth>3</depth>
	</size>
	<segmented>0</segmented>
	<object>
		<name>Plate</name>
		<pose>Unspecified</pose>
		<truncated>0</truncated>
		<difficult>0</difficult>
		<occluded>0</occluded>
		<bndbox>
			<xmin>93</xmin>
			<xmax>192</xmax>
			<ymin>425</ymin>
			<ymax>500</ymax>
		</bndbox>
	</object>
</annotation>
