<annotation>
	<folder></folder>
	<filename>video11_2370_jpg.rf.ad86a648a2db49e4483cc2f4e41b5ad7.jpg</filename>
	<path>video11_2370_jpg.rf.ad86a648a2db49e4483cc2f4e41b5ad7.jpg</path>
	<source>
		<database>roboflow.com</database>
	</source>
	<size>
		<width>640</width>
		<height>640</height>
		<depth>3</depth>
	</size>
	<segmented>0</segmented>
	<object>
		<name>Plate</name>
		<pose>Unspecified</pose>
		<truncated>0</truncated>
		<difficult>0</difficult>
		<occluded>0</occluded>
		<bndbox>
			<xmin>100</xmin>
			<xmax>260</xmax>
			<ymin>72</ymin>
			<ymax>163</ymax>
		</bndbox>
	</object>
</annotation>
